[
  {
    "residency_state_group": "NYC",
    "age_group": "18+",
    "max_date_2": "True",
    "cumulative_or_daily": "Cumulative",
    "date": "3/17/2021",
    "max_date": "3/18/2021",
    "residency_state": "NYC",
    "fully_vaccinated": "812523",
    "partially_vaccinated": "850113",
    "at_least_one_dose": "1662636",
    "n_at_least_1_dose": "1662636",
    "n_at_least_1_dose_copy": "1662636",
    "n_fully_vaccinated_cumulative": "812523",
    "n_partially_vaccinated_cumulative": "850113",
    "number_of_records": "1"
  },
  {
    "residency_state_group": "Non-NYC",
    "age_group": "18+",
    "max_date_2": "True",
    "cumulative_or_daily": "Cumulative",
    "date": "3/17/2021",
    "max_date": "3/18/2021",
    "residency_state": "NY State",
    "fully_vaccinated": "183257",
    "partially_vaccinated": "161281",
    "at_least_one_dose": "344538",
    "n_at_least_1_dose": "344538",
    "n_at_least_1_dose_copy": "344538",
    "n_fully_vaccinated_cumulative": "183257",
    "n_partially_vaccinated_cumulative": "161281",
    "number_of_records": "1"
  },
  {
    "residency_state_group": "Non-NYC",
    "age_group": "18+",
    "max_date_2": "True",
    "cumulative_or_daily": "Cumulative",
    "date": "3/17/2021",
    "max_date": "3/18/2021",
    "residency_state": "New Jersey",
    "fully_vaccinated": "34282",
    "partially_vaccinated": "19975",
    "at_least_one_dose": "54257",
    "n_at_least_1_dose": "54257",
    "n_at_least_1_dose_copy": "54257",
    "n_fully_vaccinated_cumulative": "34282",
    "n_partially_vaccinated_cumulative": "19975",
    "number_of_records": "1"
  },
  {
    "residency_state_group": "Non-NYC",
    "age_group": "18+",
    "max_date_2": "True",
    "cumulative_or_daily": "Cumulative",
    "date": "3/17/2021",
    "max_date": "3/18/2021",
    "residency_state": "Connecticut",
    "fully_vaccinated": "3943",
    "partially_vaccinated": "1648",
    "at_least_one_dose": "5591",
    "n_at_least_1_dose": "5591",
    "n_at_least_1_dose_copy": "5591",
    "n_fully_vaccinated_cumulative": "3943",
    "n_partially_vaccinated_cumulative": "1648",
    "number_of_records": "1"
  },
  {
    "residency_state_group": "Non-NYC",
    "age_group": "18+",
    "max_date_2": "True",
    "cumulative_or_daily": "Cumulative",
    "date": "3/17/2021",
    "max_date": "3/18/2021",
    "residency_state": "Other",
    "fully_vaccinated": "10136",
    "partially_vaccinated": "5967",
    "at_least_one_dose": "16103",
    "n_at_least_1_dose": "16103",
    "n_at_least_1_dose_copy": "16103",
    "n_fully_vaccinated_cumulative": "10136",
    "n_partially_vaccinated_cumulative": "5967",
    "number_of_records": "1"
  },
  {
    "residency_state_group": "Non-NYC",
    "age_group": "18+",
    "max_date_2": "True",
    "cumulative_or_daily": "Cumulative",
    "date": "3/17/2021",
    "max_date": "3/18/2021",
    "residency_state": "Unknown",
    "fully_vaccinated": "14930",
    "partially_vaccinated": "12944",
    "at_least_one_dose": "27874",
    "n_at_least_1_dose": "27874",
    "n_at_least_1_dose_copy": "27874",
    "n_fully_vaccinated_cumulative": "14930",
    "n_partially_vaccinated_cumulative": "12944",
    "number_of_records": "1"
  }
]