[
  {
    "residency_state_group": "NYC",
    "age_group": "18+",
    "max_date_2": "True",
    "cumulative_or_daily": "Cumulative",
    "date": "3/24/2021",
    "max_date": "3/25/2021",
    "residency_state": "NYC",
    "fully_vaccinated": "989567",
    "partially_vaccinated": "947452",
    "at_least_one_dose": "1937019",
    "n_at_least_1_dose": "1937019",
    "n_at_least_1_dose_copy": "1937019",
    "n_fully_vaccinated_cumulative": "989567",
    "n_partially_vaccinated_cumulative": "947452",
    "number_of_records": "1"
  },
  {
    "residency_state_group": "Non-NYC",
    "age_group": "18+",
    "max_date_2": "True",
    "cumulative_or_daily": "Cumulative",
    "date": "3/24/2021",
    "max_date": "3/25/2021",
    "residency_state": "NY State",
    "fully_vaccinated": "202296",
    "partially_vaccinated": "173188",
    "at_least_one_dose": "375484",
    "n_at_least_1_dose": "375484",
    "n_at_least_1_dose_copy": "375484",
    "n_fully_vaccinated_cumulative": "202296",
    "n_partially_vaccinated_cumulative": "173188",
    "number_of_records": "1"
  },
  {
    "residency_state_group": "Non-NYC",
    "age_group": "18+",
    "max_date_2": "True",
    "cumulative_or_daily": "Cumulative",
    "date": "3/24/2021",
    "max_date": "3/25/2021",
    "residency_state": "New Jersey",
    "fully_vaccinated": "37846",
    "partially_vaccinated": "23498",
    "at_least_one_dose": "61344",
    "n_at_least_1_dose": "61344",
    "n_at_least_1_dose_copy": "61344",
    "n_fully_vaccinated_cumulative": "37846",
    "n_partially_vaccinated_cumulative": "23498",
    "number_of_records": "1"
  },
  {
    "residency_state_group": "Non-NYC",
    "age_group": "18+",
    "max_date_2": "True",
    "cumulative_or_daily": "Cumulative",
    "date": "3/24/2021",
    "max_date": "3/25/2021",
    "residency_state": "Connecticut",
    "fully_vaccinated": "4328",
    "partially_vaccinated": "1983",
    "at_least_one_dose": "6311",
    "n_at_least_1_dose": "6311",
    "n_at_least_1_dose_copy": "6311",
    "n_fully_vaccinated_cumulative": "4328",
    "n_partially_vaccinated_cumulative": "1983",
    "number_of_records": "1"
  },
  {
    "residency_state_group": "Non-NYC",
    "age_group": "18+",
    "max_date_2": "True",
    "cumulative_or_daily": "Cumulative",
    "date": "3/24/2021",
    "max_date": "3/25/2021",
    "residency_state": "Other",
    "fully_vaccinated": "11405",
    "partially_vaccinated": "7299",
    "at_least_one_dose": "18704",
    "n_at_least_1_dose": "18704",
    "n_at_least_1_dose_copy": "18704",
    "n_fully_vaccinated_cumulative": "11405",
    "n_partially_vaccinated_cumulative": "7299",
    "number_of_records": "1"
  },
  {
    "residency_state_group": "Non-NYC",
    "age_group": "18+",
    "max_date_2": "True",
    "cumulative_or_daily": "Cumulative",
    "date": "3/24/2021",
    "max_date": "3/25/2021",
    "residency_state": "Unknown",
    "fully_vaccinated": "15327",
    "partially_vaccinated": "12008",
    "at_least_one_dose": "27335",
    "n_at_least_1_dose": "27335",
    "n_at_least_1_dose_copy": "27335",
    "n_fully_vaccinated_cumulative": "15327",
    "n_partially_vaccinated_cumulative": "12008",
    "number_of_records": "1"
  }
]